komby/__init__.py
komby/komby.py
komby/py.typed
komby-1.2.dist-info/LICENSE
komby-1.2.dist-info/METADATA
komby-1.2.dist-info/WHEEL
komby-1.2.dist-info/top_level.txt
komby-1.2.dist-info/RECORD
